netbox_metrics_ext/__init__.py
netbox_metrics_ext/metrics.py
netbox_metrics_ext/version.py
netbox_metrics_ext/api/__init__.py
netbox_metrics_ext/api/urls.py
netbox_metrics_ext/api/views.py
netbox_metrics_ext/management/__init__.py
netbox_metrics_ext/management/commands/__init__.py
netbox_metrics_ext/management/commands/rqworker_metrics.py
netbox_metrics_ext/tests/__init__.py
netbox_metrics_ext/tests/test_endpoints.py
netbox_metrics_ext/tests/test_registry.py
sample_metric_folder/__init__.py
sample_metric_folder/custom_metric.py
netbox_metrics-2.0.0.dist-info/LICENSE
netbox_metrics-2.0.0.dist-info/METADATA
netbox_metrics-2.0.0.dist-info/WHEEL
netbox_metrics-2.0.0.dist-info/top_level.txt
netbox_metrics-2.0.0.dist-info/RECORD
