Metadata-Version: 2.1
Name: netbox-metrics
Version: 2.0.0
Summary: Plugin to improve the instrumentation of NetBox and expose additional metrics (Application Metrics, RQ Worker).
Home-page: https://github.com/renatoalmeidaoliveira/nbrisk
Author: Renato Almdida Oliveira
Author-email: renato.almeida.oliveira@gmail.com
Classifier: Development Status :: 2 - Pre-Alpha
Classifier: Framework :: Django
Classifier: Programming Language :: Python :: 3
License-File: LICENSE
